scripts/__init__.py
scripts/server_tools.py
scripts/servertools.py
servertools/__init__.py
servertools/appdirs.py
servertools/data/i18n/de/LC_MESSAGES/ServerTools.mo
servertools/data/i18n/de_DE/LC_MESSAGES/ServerTools.mo
servertools/plugins/Categories.py
servertools/plugins/__init__.py
servertools/plugins/mittwaldserver.py
servertools-1.1.2.dist-info/LICENSE.md
servertools-1.1.2.dist-info/LICENSE.txt
servertools-1.1.2.dist-info/METADATA
servertools-1.1.2.dist-info/WHEEL
servertools-1.1.2.dist-info/entry_points.txt
servertools-1.1.2.dist-info/top_level.txt
servertools-1.1.2.dist-info/zip-safe
servertools-1.1.2.dist-info/RECORD
