Metadata-Version: 2.1
Name: servertools
Version: 1.1.2
Summary: administration tools for specific servers
Home-page: https://github.com/michagrandel/servertools
Author: Micha Grandel
Author-email: talk@michagrandel.de
Maintainer: Micha Grandel
Maintainer-email: talk@michagrandel.de
License: UNKNOWN
Download-URL: https://github.com/michagrandel/servertools/archive/v1.1.2.tar.gz
Keywords: server admin tools
Platform: UNKNOWN
Classifier: Development Status :: 4 - Beta
Classifier: Intended Audience :: System Administrators
Classifier: Topic :: Internet :: WWW/HTTP :: Site Management
Classifier: Topic :: System :: Systems Administration
Classifier: License :: OSI Approved :: Apache Software License
Classifier: Programming Language :: Python
Classifier: Programming Language :: Python :: 3.5
Classifier: Programming Language :: Python :: 3.6
Classifier: Programming Language :: Python :: 3.7
Classifier: Operating System :: Microsoft
Classifier: Operating System :: Microsoft :: Windows
Classifier: Operating System :: Microsoft :: Windows :: Windows 10
Classifier: Operating System :: OS Independent
Classifier: Operating System :: POSIX :: Linux
Classifier: Natural Language :: English
Classifier: Natural Language :: German
Requires-Dist: yapsy (>=1.12)
Requires-Dist: docutils (>=0.14)
Requires-Dist: pip (>=10)
Requires-Dist: setuptools (>=39)
Requires-Dist: wheel (>=0.32)
Provides-Extra: dev
Provides-Extra: test
